<?xml version="1.0" encoding="utf-8"?>
<nrml
xmlns="http://openquake.org/xmlns/nrml/0.5"
xmlns:gml="http://www.opengis.net/gml"
>
    <hazardCurves
    IMT="PGA"
    investigationTime="50.0"
    quantileValue="0.1"
    statistics="quantile"
    >
        <IMLs>
            1.000000000E-02 1.500000000E-02 2.200000000E-02 3.300000000E-02 4.700000000E-02 6.800000000E-02 1.000000000E-01 1.500000000E-01 2.200000000E-01 3.300000000E-01 4.700000000E-01 6.800000000E-01 1.000000000E+00 1.500000000E+00 2.200000000E+00 3.300000000E+00
        </IMLs>
        <hazardCurve>
            <gml:Point>
                <gml:pos>
                    28.25 36.85
                </gml:pos>
            </gml:Point>
            <poEs>
                1.000000000E+00 1.000000000E+00 1.000000000E+00 9.999999317E-01 9.999776361E-01 9.986788088E-01 9.786236759E-01 8.669519738E-01 6.305112430E-01 3.381253088E-01 1.498541184E-01 5.050870266E-02 1.241573397E-02 1.974494946E-03 1.144494793E-04 0.000000000E+00
            </poEs>
        </hazardCurve>
    </hazardCurves>
</nrml>
