<?xml version="1.0" encoding="utf-8"?>
<nrml
xmlns="http://openquake.org/xmlns/nrml/0.5"
xmlns:gml="http://www.opengis.net/gml"
>
    <hazardCurves
    IMT="SA"
    investigationTime="50.0"
    quantileValue="0.5"
    saDamping="5.0"
    saPeriod="3.0"
    statistics="quantile"
    >
        <IMLs>
            2.200000000E-03 3.300000000E-03 4.700000000E-03 6.800000000E-03 1.000000000E-02 1.500000000E-02 2.200000000E-02 3.300000000E-02 4.700000000E-02 6.800000000E-02 1.000000000E-01 1.500000000E-01 2.200000000E-01 3.300000000E-01 4.700000000E-01 6.800000000E-01 1.000000000E+00 1.500000000E+00 2.200000000E+00
        </IMLs>
        <hazardCurve>
            <gml:Point>
                <gml:pos>
                    28.25 36.85
                </gml:pos>
            </gml:Point>
            <poEs>
                9.999999997E-01 9.999996036E-01 9.999657939E-01 9.990272175E-01 9.884294776E-01 9.341770116E-01 8.074781817E-01 6.025506845E-01 4.121582802E-01 2.490577076E-01 1.295215094E-01 5.680398955E-02 2.273191850E-02 7.655118005E-03 2.561675266E-03 5.786367404E-04 7.833365167E-05 1.810703033E-06 0.000000000E+00
            </poEs>
        </hazardCurve>
    </hazardCurves>
</nrml>
